requirements.txt
setup.py
django_meta_tag_view/__init__.py
django_meta_tag_view/views.py
django_meta_tag_view.egg-info/PKG-INFO
django_meta_tag_view.egg-info/SOURCES.txt
django_meta_tag_view.egg-info/dependency_links.txt
django_meta_tag_view.egg-info/requires.txt
django_meta_tag_view.egg-info/top_level.txt