Metadata-Version: 2.1
Name: django-meta-tag-view
Version: 2020.7.1
Summary: Django <meta /> tag view mixin
Home-page: https://github.com/andrewp-as-is/django-meta-tag-view.py
License: Unlicense
Keywords: django meta
Platform: UNKNOWN
Classifier: Framework :: Django
Classifier: License :: Public Domain
Classifier: Operating System :: OS Independent
Classifier: Programming Language :: Python :: 3
